requests_ecp/__init__.py
requests_ecp/auth.py
requests_ecp/ecp.py
requests_ecp/session.py
requests_ecp/tests/__init__.py
requests_ecp/tests/test_auth.py
requests_ecp/tests/test_ecp.py
requests_ecp/tests/test_session.py
requests_ecp-0.3.2.dist-info/LICENSE
requests_ecp-0.3.2.dist-info/METADATA
requests_ecp-0.3.2.dist-info/WHEEL
requests_ecp-0.3.2.dist-info/top_level.txt
requests_ecp-0.3.2.dist-info/RECORD
