Metadata-Version: 2.1
Name: requests-ecp
Version: 0.3.2
Summary: SAML/ECP authentication handler for python-requests
Author-email: Duncan Macleod <duncan.macleod@ligo.org>
License: GPL-3.0-or-later
Project-URL: Bug Tracker, https://git.ligo.org/computing/software/requests-ecp/-/issues
Project-URL: Documentation, https://requests-ecp.readthedocs.io/
Project-URL: Source Code, https://git.ligo.org/computing/software/requests-ecp/
Classifier: Development Status :: 4 - Beta
Classifier: Intended Audience :: Science/Research
Classifier: License :: OSI Approved :: GNU General Public License v3 or later (GPLv3+)
Classifier: Natural Language :: English
Classifier: Operating System :: OS Independent
Classifier: Programming Language :: Python :: 3
Classifier: Programming Language :: Python :: 3.6
Classifier: Programming Language :: Python :: 3.7
Classifier: Programming Language :: Python :: 3.8
Classifier: Programming Language :: Python :: 3.9
Classifier: Programming Language :: Python :: 3.10
Classifier: Programming Language :: Python :: 3.11
Classifier: Programming Language :: Python :: 3.12
Classifier: Topic :: Scientific/Engineering
Requires-Python: >=3.6
License-File: LICENSE
Requires-Dist: lxml
Requires-Dist: requests
Provides-Extra: docs
Requires-Dist: furo ; extra == 'docs'
Requires-Dist: sphinx ; extra == 'docs'
Requires-Dist: sphinx-argparse ; extra == 'docs'
Requires-Dist: sphinx-design ; extra == 'docs'
Requires-Dist: sphinx-automodapi ; extra == 'docs'
Provides-Extra: kerberos
Requires-Dist: requests-gssapi >=1.2.2 ; extra == 'kerberos'
Provides-Extra: tests
Requires-Dist: pytest >=2.9.2 ; extra == 'tests'
Requires-Dist: pytest-cov ; extra == 'tests'
Requires-Dist: requests-mock >=1.5.0 ; extra == 'tests'
